setup.py
toolsbyerazhan/__init__.py
toolsbyerazhan/gputools.py
toolsbyerazhan/jsontools.py
toolsbyerazhan/ostools.py
toolsbyerazhan/quicktools.py
toolsbyerazhan/timetools.py
toolsbyerazhan.egg-info/PKG-INFO
toolsbyerazhan.egg-info/SOURCES.txt
toolsbyerazhan.egg-info/dependency_links.txt
toolsbyerazhan.egg-info/top_level.txt
toolsbyerazhan/layers/__init__.py
toolsbyerazhan/layers/crf_layer.py
toolsbyerazhan/layers/tfa_crf.py
toolsbyerazhan/models/BiLSTMCRF.py
toolsbyerazhan/models/MVLSTM.py
toolsbyerazhan/models/__init__.py
toolsbyerazhan/pandastools/__init__.py
toolsbyerazhan/pandastools/pd__read_csv.py
toolsbyerazhan/sklearntools/__init__.py
toolsbyerazhan/sklearntools/sklearn_basic_usage.py
toolsbyerazhan/sklearntools/sklearn_ensemble.py
toolsbyerazhan/sklearntools/sklearn_naive_bayes.py
toolsbyerazhan/tensorflowtools/__init__.py
toolsbyerazhan/tensorflowtools/tf__keras__layers.py
toolsbyerazhan/tensorflowtools/tf__linalg__band_part.py
toolsbyerazhan/tensorflowtools/tf__linalg__matmul.py
toolsbyerazhan/tensorflowtools/tf__shape.py
toolsbyerazhan/transformers/__init__.py
toolsbyerazhan/transformers/Bert/__init__.py
toolsbyerazhan/transformers/XLNet/__init__.py
toolsbyerazhan/transformers/XLNet/test.py
toolsbyerazhan/transformers/XLNet/test_xlnet_functions.py
toolsbyerazhan/transformers/XLNet/xlnet_configuration.py
toolsbyerazhan/transformers/XLNet/xlnet_layers.py
toolsbyerazhan/transformers/XLNet/xlnet_models.py
toolsbyerazhan/transformers/XLNet/xlnet_utils.py
toolsbyerazhan/xgboostools/__init__.py
toolsbyerazhan/xgboostools/xgb_basic_usage.py