Metadata-Version: 1.2
Name: toolsbyerazhan
Version: 0.1.14
Summary: some useful tools
Home-page: https://github.com/erazhan/CommonTools
Author: erazhan
Author-email: erazhan@163.com
License: MIT Licence
Keywords: toolsbyerazhan
Platform: any
Requires-Python: >=3.7.1
